{
	"posts": [
		{
			"id": "1",
			"title": "The Transformative Power of Technology in the Workplace: Digital Age Work Dynamics",
			"image": "https://images.unsplash.com/photo-1486312338219-ce68d2c6f44d?q=80&w=2072&auto=format&fit=crop&ixlib=rb-4.0.3&ixid=M3wxMjA3fDB8MHxwaG90by1wYWdlfHx8fGVufDB8fHx8fA%3D%3D",
			"views": 100
		},
		{
			"id": "2",
			"title": "The Future of Technology: Digital Transformation Dynamics Towards 2030",
			"image": "https://images.unsplash.com/photo-1605810230434-7631ac76ec81?q=80&w=2070&auto=format&fit=crop&ixlib=rb-4.0.3&ixid=M3wxMjA3fDB8MHxwaG90by1wYWdlfHx8fGVufDB8fHx8fA%3D%3D",
			"views": 200
		},
		{
			"id": "3",
			"title": "The Role of Technology in Education: The Learning Revolution in the Digital Age",
			"image": "https://images.unsplash.com/photo-1519389950473-47ba0277781c?q=80&w=2070&auto=format&fit=crop&ixlib=rb-4.0.3&ixid=M3wxMjA3fDB8MHxwaG90by1wYWdlfHx8fGVufDB8fHx8fA%3D%3D",
			"name": "Hikmet Melik FIRAT",
			"views": 200
		},
		{
			"id": "4",
			"title": "Revolution in Healthcare Technologies: AI and Innovation in Patient Care",
			"image": "https://images.unsplash.com/photo-1581090464777-f3220bbe1b8b?q=80&w=1974&auto=format&fit=crop&ixlib=rb-4.0.3&ixid=M3wxMjA3fDB8MHxwaG90by1wYWdlfHx8fGVufDB8fHx8fA%3D%3D",
			"name": "Jason Francisco",
			"views": 200
		},
		{
			"id": "5",
			"title": "Mental Health Guide: Strategies for Protecting Your Mental Well-being in the Modern World",
			"image": "https://plus.unsplash.com/premium_photo-1667762241847-37471e8c8bc0?q=80&w=2069&auto=format&fit=crop&ixlib=rb-4.0.3&ixid=M3wxMjA3fDB8MHxwaG90by1wYWdlfHx8fGVufDB8fHx8fA%3D%3D",
			"name": "Elizabeth Slavin",
			"views": 200
		},
		{
			"id": "6",
			"title": "Financial Freedom Roadmap: The Art of Wisely Managing Your Money",
			"image": "https://images.unsplash.com/photo-1640161704729-cbe966a08476?q=80&w=2072&auto=format&fit=crop&ixlib=rb-4.0.3&ixid=M3wxMjA3fDB8MHxwaG90by1wYWdlfHx8fGVufDB8fHx8fA%3D%3D",
			"name": "John Doe",
			"views": 200
		},
		{
			"id": "7",
			"title": "2024 Travel Guide: World Destinations Waiting to be Explored",
			"image": "https://images.unsplash.com/photo-1504598318550-17eba1008a68?q=80&w=1972&auto=format&fit=crop&ixlib=rb-4.0.3&ixid=M3wxMjA3fDB8MHxwaG90by1wYWdlfHx8fGVufDB8fHx8fA%3D%3D",
			"name": "Jane Doe",
			"views": 200
		},
		{
			"id": "8",
			"title": "Healthy Living Strategy: A Holistic Fitness Approach",
			"image": "https://images.unsplash.com/photo-1494390248081-4e521a5940db?q=80&w=2006&auto=format&fit=crop&ixlib=rb-4.0.3&ixid=M3wxMjA3fDB8MHxwaG90by1wYWdlfHx8fGVufDB8fHx8fA%3D%3D",
			"name": "Fiona Smith",
			"views": 200
		},
		{
			"id": "9",
			"title": "Nutrition Science: Fundamental Strategies for Healthy Living",
			"image": "https://images.unsplash.com/photo-1505576399279-565b52d4ac71?q=80&w=1974&auto=format&fit=crop&ixlib=rb-4.0.3&ixid=M3wxMjA3fDB8MHxwaG90by1wYWdlfHx8fGVufDB8fHx8fA%3D%3D",
			"name": "Tom Johnson",
			"views": 200
		},
		{
			"id": "10",
			"title": "The Digital Security Era: Cybersecurity and Personal Data Protection",
			"image": "https://plus.unsplash.com/premium_photo-1701179596614-9c64f50cda76?q=80&w=1974&auto=format&fit=crop&ixlib=rb-4.0.3&ixid=M3wxMjA3fDB8MHxwaG90by1wYWdlfHx8fGVufDB8fHx8fA%3D%3D",
			"name": "Alice Brown",
			"views": 200
		}
	],
	"comments": [
		{ "id": "1", "text": "a comment about post 1", "postId": "1" },
		{ "id": "2", "text": "another comment about post 1", "postId": "1" }
	]
}
