{
    "blogs": [
        {
            "id": 1,
            "title": "Next.js ile Blog Sitesi Yapımı",
            "content": "Bu yazıda Next.js ile nasıl blog sitesi yapacağınızı anlatıyoruz.",
            "author": "Hatice Özçelik",
            "date": "2025-03-10"
        },
        {
            "id": 2,
            "title": "React Server Components Nedir?",
            "content": "React Server Components hakkında temel bilgiler ve kullanım senaryoları.",
            "author": "Hazal Kütküt",
            "date": "2025-03-09"
        }
    ]
}